dixi/__init__.py
dixi/dixi.py
dixi-0.0.1.dist-info/DESCRIPTION.rst
dixi-0.0.1.dist-info/METADATA
dixi-0.0.1.dist-info/RECORD
dixi-0.0.1.dist-info/WHEEL
dixi-0.0.1.dist-info/metadata.json
dixi-0.0.1.dist-info/top_level.txt
