Metadata-Version: 2.0
Name: dixi
Version: 0.0.1
Summary: Wrapper around Python dicts that makes it easy to deal with nested tree structures.
Home-page: https://github.com/tvogels/pyexr
Author: Thijs Vogels
Author-email: t.vogels@me.com
License: BSD
Keywords: dict,tree,numpy slicing
Platform: UNKNOWN
